gavels/__init__.py
gavels-0.0.2.dist-info/METADATA
gavels-0.0.2.dist-info/WHEEL
gavels-0.0.2.dist-info/top_level.txt
gavels-0.0.2.dist-info/RECORD
