Metadata-Version: 2.4
Name: gavels
Version: 0.0.2
Summary: AI-powered judgment SDK
Author-email: Ilias Merigh <ilias@merigh.com>
License: MIT
Classifier: Development Status :: 1 - Planning
Classifier: Intended Audience :: Developers
Classifier: Programming Language :: Python :: 3
Classifier: License :: OSI Approved :: MIT License
Requires-Python: >=3.8
